pyuntar.py
PyUnTAR-4.12.0.dist-info/LICENSE
PyUnTAR-4.12.0.dist-info/METADATA
PyUnTAR-4.12.0.dist-info/WHEEL
PyUnTAR-4.12.0.dist-info/top_level.txt
PyUnTAR-4.12.0.dist-info/zip-safe
PyUnTAR-4.12.0.dist-info/RECORD
